{
    "475d616f-52db-3b8a-9f15-e101ec5436d1": {
        "uuid": "475d616f-52db-3b8a-9f15-e101ec5436d1",
        "title": "3 Questions That 3M Needs to Answer",
        "publisher": "Motley Fool",
        "link": "https://finance.yahoo.com/m/475d616f-52db-3b8a-9f15-e101ec5436d1/3-questions-that-3m-needs-to.html",
        "providerPublishTime": 1657118700,
        "type": "STORY",
        "relatedTickers": [
            "MMM"
        ]
    },
    "a45d9425-675d-3828-af0a-c03c64031391": {
        "uuid": "a45d9425-675d-3828-af0a-c03c64031391",
        "title": "Dow 30 Stocks Listed and Ranked By 2022 Hedge Fund Bullishness Index",
        "publisher": "Insider Monkey",
        "link": "https://finance.yahoo.com/news/dow-30-stocks-listed-ranked-135249329.html",
        "providerPublishTime": 1657115989,
        "type": "STORY",
        "thumbnail": {
            "resolutions": [
                {
                    "url": "https://s.yimg.com/uu/api/res/1.2/EZiNUwcsUGsmI1YmJMMKng--~B/aD01MDA7dz03NTA7YXBwaWQ9eXRhY2h5b24-/https://s.yimg.com/uu/api/res/1.2/wwGJ9vxzwe7jH6wO0F.1SQ--~B/aD01MDA7dz03NTA7YXBwaWQ9eXRhY2h5b24-/https://media.zenfs.com/en/insidermonkey.com/a1736860ba5597c44234e52f8b57cad2",
                    "width": 750,
                    "height": 500,
                    "tag": "original"
                },
                {
                    "url": "https://s.yimg.com/uu/api/res/1.2/qUBx2ZNxTJD6llOAbFYB8A--~B/Zmk9ZmlsbDtoPTE0MDtweW9mZj0wO3c9MTQwO2FwcGlkPXl0YWNoeW9u/https://s.yimg.com/uu/api/res/1.2/wwGJ9vxzwe7jH6wO0F.1SQ--~B/aD01MDA7dz03NTA7YXBwaWQ9eXRhY2h5b24-/https://media.zenfs.com/en/insidermonkey.com/a1736860ba5597c44234e52f8b57cad2",
                    "width": 140,
                    "height": 140,
                    "tag": "140x140"
                }
            ]
        },
        "relatedTickers": [
            "CAT",
            "^DJI",
            "IBM",
            "KO",
            "CSCO",
            "TRV",
            "AMGN",
            "NKE",
            "HON",
            "CVX",
            "WBA",
            "WMT",
            "MMM",
            "BA",
            "MCD",
            "DOW"
        ]
    },
    "ef456de0-3a3e-32ef-af1d-23837a8853fc": {
        "uuid": "ef456de0-3a3e-32ef-af1d-23837a8853fc",
        "title": "This Dow Jones Stock Has a Huge Risk You Might Not Know About",
        "publisher": "Motley Fool",
        "link": "https://finance.yahoo.com/m/ef456de0-3a3e-32ef-af1d-23837a8853fc/this-dow-jones-stock-has-a.html",
        "providerPublishTime": 1657105500,
        "type": "STORY",
        "thumbnail": {
            "resolutions": [
                {
                    "url": "https://s.yimg.com/uu/api/res/1.2/cWZA2jXRkkry.79Y8Eksmw--~B/aD04NDA7dz0xNDAwO2FwcGlkPXl0YWNoeW9u/https://s.yimg.com/uu/api/res/1.2/K_URyIfH73EDaqyLko2fWw--~B/aD04NDA7dz0xNDAwO2FwcGlkPXl0YWNoeW9u/https://media.zenfs.com/en/motleyfool.com/1a6d69f9f74fc147e789bfd163ee64ef",
                    "width": 1400,
                    "height": 840,
                    "tag": "original"
                },
                {
                    "url": "https://s.yimg.com/uu/api/res/1.2/lPqyDDdaNQ2wg7W.LBA1gA--~B/Zmk9ZmlsbDtoPTE0MDtweW9mZj0wO3c9MTQwO2FwcGlkPXl0YWNoeW9u/https://s.yimg.com/uu/api/res/1.2/K_URyIfH73EDaqyLko2fWw--~B/aD04NDA7dz0xNDAwO2FwcGlkPXl0YWNoeW9u/https://media.zenfs.com/en/motleyfool.com/1a6d69f9f74fc147e789bfd163ee64ef",
                    "width": 140,
                    "height": 140,
                    "tag": "140x140"
                }
            ]
        },
        "relatedTickers": [
            "MMM"
        ]
    },
    "cd710ab5-5ca6-32e8-b33c-d7e4c32c08d9": {
        "uuid": "cd710ab5-5ca6-32e8-b33c-d7e4c32c08d9",
        "title": "Agreement Reached Between the Flemish Government and 3M Belgium to Support the People of Flanders",
        "publisher": "PR Newswire",
        "link": "https://finance.yahoo.com/news/agreement-reached-between-flemish-government-104500233.html",
        "providerPublishTime": 1657104300,
        "type": "STORY",
        "thumbnail": {
            "resolutions": [
                {
                    "url": "https://s.yimg.com/uu/api/res/1.2/mV4B3FrzdtO93UP.k5568g--~B/aD0xNjt3PTE2O2FwcGlkPXl0YWNoeW9u/https://s.yimg.com/uu/api/res/1.2/p4DZmlhLcUBQgUtZ5cdVQw--~B/aD0xNjt3PTE2O2FwcGlkPXl0YWNoeW9u/https://media.zenfs.com/en/prnewswire.com/ff66f42dfeac8b9f54f000d63beec5bb",
                    "width": 16,
                    "height": 16,
                    "tag": "original"
                },
                {
                    "url": "https://s.yimg.com/uu/api/res/1.2/jHfInyRR1NfeRTyuffu7mg--~B/Zmk9ZmlsbDtoPTE0MDtweW9mZj0wO3c9MTQwO2FwcGlkPXl0YWNoeW9u/https://s.yimg.com/uu/api/res/1.2/p4DZmlhLcUBQgUtZ5cdVQw--~B/aD0xNjt3PTE2O2FwcGlkPXl0YWNoeW9u/https://media.zenfs.com/en/prnewswire.com/ff66f42dfeac8b9f54f000d63beec5bb",
                    "width": 140,
                    "height": 140,
                    "tag": "140x140"
                }
            ]
        },
        "relatedTickers": [
            "MMM"
        ]
    },
    "bb1b3744-0b23-39a5-9f5c-078d2be100b8": {
        "uuid": "bb1b3744-0b23-39a5-9f5c-078d2be100b8",
        "title": "3M (MMM) to Divest Neoplast & Neobun Brands to Selic Corp",
        "publisher": "Zacks",
        "link": "https://finance.yahoo.com/news/3m-mmm-divest-neoplast-neobun-154403884.html",
        "providerPublishTime": 1656949443,
        "type": "STORY",
        "thumbnail": {
            "resolutions": [
                {
                    "url": "https://s.yimg.com/uu/api/res/1.2/D5EFjYN5cJ45vQ6rxXQwiA--~B/aD00MDA7dz02MzU7YXBwaWQ9eXRhY2h5b24-/https://s.yimg.com/uu/api/res/1.2/KrJm9ktFdJz09QZArKeMUA--~B/aD00MDA7dz02MzU7YXBwaWQ9eXRhY2h5b24-/https://media.zenfs.com/en/zacks.com/3c91a0562c12b43bce0ef8ba5b7cd83e",
                    "width": 635,
                    "height": 400,
                    "tag": "original"
                },
                {
                    "url": "https://s.yimg.com/uu/api/res/1.2/R4cO8Z40V6zok2s6dXaeEg--~B/Zmk9ZmlsbDtoPTE0MDtweW9mZj0wO3c9MTQwO2FwcGlkPXl0YWNoeW9u/https://s.yimg.com/uu/api/res/1.2/KrJm9ktFdJz09QZArKeMUA--~B/aD00MDA7dz02MzU7YXBwaWQ9eXRhY2h5b24-/https://media.zenfs.com/en/zacks.com/3c91a0562c12b43bce0ef8ba5b7cd83e",
                    "width": 140,
                    "height": 140,
                    "tag": "140x140"
                }
            ]
        },
        "relatedTickers": [
            "MMM",
            "GFF",
            "CSL"
        ]
    },
    "92ebd894-db8b-37e3-b90b-aa483b7f45a2": {
        "uuid": "92ebd894-db8b-37e3-b90b-aa483b7f45a2",
        "title": "3M Divests Neoplast, Neobun Rights, Related Assets In Thailand & Southeast Asia",
        "publisher": "Benzinga",
        "link": "https://finance.yahoo.com/news/3m-divests-neoplast-neobun-rights-151623258.html",
        "providerPublishTime": 1656688583,
        "type": "STORY",
        "thumbnail": {
            "resolutions": [
                {
                    "url": "https://s.yimg.com/uu/api/res/1.2/Zfu1_RwugQjyBBN8fUCqcw--~B/aD00MDA7dz02MDA7YXBwaWQ9eXRhY2h5b24-/https://s.yimg.com/uu/api/res/1.2/54v76O12XShpM0X_wOaSvA--~B/aD00MDA7dz02MDA7YXBwaWQ9eXRhY2h5b24-/https://media.zenfs.com/en/Benzinga/9ea7dc3bf13378378f0284f8c6fbc82f",
                    "width": 600,
                    "height": 400,
                    "tag": "original"
                },
                {
                    "url": "https://s.yimg.com/uu/api/res/1.2/KHLWsr2QBALwNnFNqioicQ--~B/Zmk9ZmlsbDtoPTE0MDtweW9mZj0wO3c9MTQwO2FwcGlkPXl0YWNoeW9u/https://s.yimg.com/uu/api/res/1.2/54v76O12XShpM0X_wOaSvA--~B/aD00MDA7dz02MDA7YXBwaWQ9eXRhY2h5b24-/https://media.zenfs.com/en/Benzinga/9ea7dc3bf13378378f0284f8c6fbc82f",
                    "width": 140,
                    "height": 140,
                    "tag": "140x140"
                }
            ]
        },
        "relatedTickers": [
            "MMM"
        ]
    },
    "b4fce880-71e2-34ca-ae1f-74ec2a9ea1e5": {
        "uuid": "b4fce880-71e2-34ca-ae1f-74ec2a9ea1e5",
        "title": "Micron, Kohl's, Apple Fall Premarket; Nio Climbs",
        "publisher": "Investing.com",
        "link": "https://finance.yahoo.com/news/micron-kohls-apple-fall-premarket-075251139.html",
        "providerPublishTime": 1656661971,
        "type": "STORY",
        "relatedTickers": [
            "AAPL",
            "MU",
            "KSS",
            "FDX",
            "MMM",
            "C"
        ]
    },
    "2f5a6fc3-a5ea-3077-9593-8c8cef964d90": {
        "uuid": "2f5a6fc3-a5ea-3077-9593-8c8cef964d90",
        "title": "3M to exit Neoplast, Neobun brands in Southeast Asia",
        "publisher": "Reuters",
        "link": "https://finance.yahoo.com/news/3m-exit-neoplast-neobun-brands-045930810.html",
        "providerPublishTime": 1656651570,
        "type": "STORY",
        "thumbnail": {
            "resolutions": [
                {
                    "url": "https://s.yimg.com/uu/api/res/1.2/j7Awnu1bKMcM_7T6s0iSIg--~B/aD01MzQ7dz04MDA7YXBwaWQ9eXRhY2h5b24-/https://s.yimg.com/uu/api/res/1.2/hY81IidOYRV5Sk23f0nQKg--~B/aD01MzQ7dz04MDA7YXBwaWQ9eXRhY2h5b24-/https://media.zenfs.com/en/reuters-finance.com/c3a153cf696762b0ac668ca480a2fa88",
                    "width": 800,
                    "height": 534,
                    "tag": "original"
                },
                {
                    "url": "https://s.yimg.com/uu/api/res/1.2/Ku8bdWlfhGFJWUEpdR1i9w--~B/Zmk9ZmlsbDtoPTE0MDtweW9mZj0wO3c9MTQwO2FwcGlkPXl0YWNoeW9u/https://s.yimg.com/uu/api/res/1.2/hY81IidOYRV5Sk23f0nQKg--~B/aD01MzQ7dz04MDA7YXBwaWQ9eXRhY2h5b24-/https://media.zenfs.com/en/reuters-finance.com/c3a153cf696762b0ac668ca480a2fa88",
                    "width": 140,
                    "height": 140,
                    "tag": "140x140"
                }
            ]
        },
        "relatedTickers": [
            "MMM"
        ]
    }
}