{
    "4c1717b0-9d3a-3b83-a151-08a845d2d8e7": {
        "uuid": "4c1717b0-9d3a-3b83-a151-08a845d2d8e7",
        "title": "Amazon Gets First Rivian Vans on the Road",
        "publisher": "TheStreet.com",
        "link": "https://finance.yahoo.com/m/4c1717b0-9d3a-3b83-a151-08a845d2d8e7/amazon-gets-first-rivian-vans.html",
        "providerPublishTime": 1658574900,
        "type": "STORY",
        "thumbnail": {
            "resolutions": [
                {
                    "url": "https://s.yimg.com/uu/api/res/1.2/xdgQxGfHXQ4QMc2_I1BLtg--~B/aD0xMDgwO3c9MTkyMDthcHBpZD15dGFjaHlvbg--/https://s.yimg.com/uu/api/res/1.2/uzMWWZpI05yPe79ClI4tfA--~B/aD0xMDgwO3c9MTkyMDthcHBpZD15dGFjaHlvbg--/https://media.zenfs.com/en/thestreet.com/2bf598b25637bb67513659e66ae4604d",
                    "width": 1920,
                    "height": 1080,
                    "tag": "original"
                },
                {
                    "url": "https://s.yimg.com/uu/api/res/1.2/KWePSWK52EI4753_Jd.slw--~B/Zmk9ZmlsbDtoPTE0MDtweW9mZj0wO3c9MTQwO2FwcGlkPXl0YWNoeW9u/https://s.yimg.com/uu/api/res/1.2/uzMWWZpI05yPe79ClI4tfA--~B/aD0xMDgwO3c9MTkyMDthcHBpZD15dGFjaHlvbg--/https://media.zenfs.com/en/thestreet.com/2bf598b25637bb67513659e66ae4604d",
                    "width": 140,
                    "height": 140,
                    "tag": "140x140"
                }
            ]
        },
        "relatedTickers": [
            "RIVN",
            "AMZN"
        ]
    },
    "4b7a0129-a1e2-3e16-be01-f4acb133db02": {
        "uuid": "4b7a0129-a1e2-3e16-be01-f4acb133db02",
        "title": "Amazon Starts Using Rivian's Electric Vehicles. Is It Time to Buy This EV Stock?",
        "publisher": "Motley Fool",
        "link": "https://finance.yahoo.com/m/4b7a0129-a1e2-3e16-be01-f4acb133db02/amazon-starts-using-rivian%27s.html",
        "providerPublishTime": 1658573700,
        "type": "STORY",
        "thumbnail": {
            "resolutions": [
                {
                    "url": "https://s.yimg.com/uu/api/res/1.2/swTj_jSIDSPKgxTHuwoN9w--~B/aD05MzM7dz0xNDAwO2FwcGlkPXl0YWNoeW9u/https://s.yimg.com/uu/api/res/1.2/OdDhs5BjKIJXy93GZoLaSQ--~B/aD05MzM7dz0xNDAwO2FwcGlkPXl0YWNoeW9u/https://media.zenfs.com/en/motleyfool.com/8d8ad530230850f13e4c1282fafedec9",
                    "width": 1400,
                    "height": 933,
                    "tag": "original"
                },
                {
                    "url": "https://s.yimg.com/uu/api/res/1.2/GthgtI1DWzbPAu6qhQAOXA--~B/Zmk9ZmlsbDtoPTE0MDtweW9mZj0wO3c9MTQwO2FwcGlkPXl0YWNoeW9u/https://s.yimg.com/uu/api/res/1.2/OdDhs5BjKIJXy93GZoLaSQ--~B/aD05MzM7dz0xNDAwO2FwcGlkPXl0YWNoeW9u/https://media.zenfs.com/en/motleyfool.com/8d8ad530230850f13e4c1282fafedec9",
                    "width": 140,
                    "height": 140,
                    "tag": "140x140"
                }
            ]
        },
        "relatedTickers": [
            "RIVN",
            "AMZN"
        ]
    },
    "96b11239-0657-32f0-9934-686fc0c45969": {
        "uuid": "96b11239-0657-32f0-9934-686fc0c45969",
        "title": "Amazon's Billion-Dollar Deal: Here's What You Need to Know",
        "publisher": "Motley Fool",
        "link": "https://finance.yahoo.com/m/96b11239-0657-32f0-9934-686fc0c45969/amazon%27s-billion-dollar-deal%3A.html",
        "providerPublishTime": 1658572200,
        "type": "STORY",
        "relatedTickers": [
            "AMZN",
            "ONEM",
            "TDOC"
        ]
    },
    "1f1ff8e5-fe65-3c55-bb69-5f58c09fa7d8": {
        "uuid": "1f1ff8e5-fe65-3c55-bb69-5f58c09fa7d8",
        "title": "Apple, Amazon, Meta Highlight Tech-Heavy Earnings Week",
        "publisher": "The Wall Street Journal",
        "link": "https://finance.yahoo.com/m/1f1ff8e5-fe65-3c55-bb69-5f58c09fa7d8/apple%2C-amazon%2C-meta-highlight.html",
        "providerPublishTime": 1658568600,
        "type": "STORY",
        "thumbnail": {
            "resolutions": [
                {
                    "url": "https://s.yimg.com/uu/api/res/1.2/hTLip36u10_.z25DbZfmaA--~B/aD02NDA7dz0xMjgwO2FwcGlkPXl0YWNoeW9u/https://s.yimg.com/uu/api/res/1.2/aNFTW6Iim_1GpCCEl6Ws3A--~B/aD02NDA7dz0xMjgwO2FwcGlkPXl0YWNoeW9u/https://media.zenfs.com/en/wsj.com/b801adda1cb347f21b088060e56d5951",
                    "width": 1280,
                    "height": 640,
                    "tag": "original"
                },
                {
                    "url": "https://s.yimg.com/uu/api/res/1.2/PFb.NrvnEDJStnV2_SK5zA--~B/Zmk9ZmlsbDtoPTE0MDtweW9mZj0wO3c9MTQwO2FwcGlkPXl0YWNoeW9u/https://s.yimg.com/uu/api/res/1.2/aNFTW6Iim_1GpCCEl6Ws3A--~B/aD02NDA7dz0xMjgwO2FwcGlkPXl0YWNoeW9u/https://media.zenfs.com/en/wsj.com/b801adda1cb347f21b088060e56d5951",
                    "width": 140,
                    "height": 140,
                    "tag": "140x140"
                }
            ]
        },
        "relatedTickers": [
            "CL",
            "GM",
            "AAPL",
            "AMZN",
            "GOOG",
            "GOOGL"
        ]
    },
    "6dacf9c7-f78b-382b-8aa1-ee2d85dff95a": {
        "uuid": "6dacf9c7-f78b-382b-8aa1-ee2d85dff95a",
        "title": "Nasdaq Bear Market: 5 Astounding Growth Stocks You'll Regret Not Buying on the Dip",
        "publisher": "Motley Fool",
        "link": "https://finance.yahoo.com/m/6dacf9c7-f78b-382b-8aa1-ee2d85dff95a/nasdaq-bear-market%3A-5.html",
        "providerPublishTime": 1658568060,
        "type": "STORY",
        "thumbnail": {
            "resolutions": [
                {
                    "url": "https://s.yimg.com/uu/api/res/1.2/TD7IFot3jlQXsQeZ0bWtmg--~B/aD05MzM7dz0xNDAwO2FwcGlkPXl0YWNoeW9u/https://s.yimg.com/uu/api/res/1.2/frHlwSYNw982k_Zv8BZdAg--~B/aD05MzM7dz0xNDAwO2FwcGlkPXl0YWNoeW9u/https://media.zenfs.com/en/motleyfool.com/9f2780aa00ceafda89c0b40eddeb8fa6",
                    "width": 1400,
                    "height": 933,
                    "tag": "original"
                },
                {
                    "url": "https://s.yimg.com/uu/api/res/1.2/HMaxba41e3WLyRbZc.rKzA--~B/Zmk9ZmlsbDtoPTE0MDtweW9mZj0wO3c9MTQwO2FwcGlkPXl0YWNoeW9u/https://s.yimg.com/uu/api/res/1.2/frHlwSYNw982k_Zv8BZdAg--~B/aD05MzM7dz0xNDAwO2FwcGlkPXl0YWNoeW9u/https://media.zenfs.com/en/motleyfool.com/9f2780aa00ceafda89c0b40eddeb8fa6",
                    "width": 140,
                    "height": 140,
                    "tag": "140x140"
                }
            ]
        },
        "relatedTickers": [
            "COMP",
            "CRM",
            "PLTR",
            "AMZN",
            "PING",
            "UPST"
        ]
    },
    "691c0293-48e6-3068-9f84-bca5bcea8019": {
        "uuid": "691c0293-48e6-3068-9f84-bca5bcea8019",
        "title": "A different Middle-earth is explored in Amazon's 'Lord of the Rings' series",
        "publisher": "Reuters",
        "link": "https://finance.yahoo.com/news/different-middle-earth-explored-amazons-214600906.html",
        "providerPublishTime": 1658526360,
        "type": "STORY",
        "relatedTickers": [
            "AMZN"
        ]
    },
    "9db9bca3-3502-3f00-93f7-df1d78f93a0d": {
        "uuid": "9db9bca3-3502-3f00-93f7-df1d78f93a0d",
        "title": "Amazon policy executive Jay Carney leaves for Airbnb",
        "publisher": "American City Business Journals",
        "link": "https://finance.yahoo.com/m/9db9bca3-3502-3f00-93f7-df1d78f93a0d/amazon-policy-executive-jay.html",
        "providerPublishTime": 1658524465,
        "type": "STORY",
        "thumbnail": {
            "resolutions": [
                {
                    "url": "https://s.yimg.com/uu/api/res/1.2/LqMoRHY6kAOvW767_1kuAA--~B/aD05NjE7dz0xNDQwO2FwcGlkPXl0YWNoeW9u/https://s.yimg.com/uu/api/res/1.2/9tOGyMYy5d6HCFrKTzG4yw--~B/aD05NjE7dz0xNDQwO2FwcGlkPXl0YWNoeW9u/https://media.zenfs.com/en/bizjournals.com/3dac5c71dcec6f23c909bd14151b3b83",
                    "width": 1440,
                    "height": 961,
                    "tag": "original"
                },
                {
                    "url": "https://s.yimg.com/uu/api/res/1.2/SzrN.JMijxmWJuQ86d1XLA--~B/Zmk9ZmlsbDtoPTE0MDtweW9mZj0wO3c9MTQwO2FwcGlkPXl0YWNoeW9u/https://s.yimg.com/uu/api/res/1.2/9tOGyMYy5d6HCFrKTzG4yw--~B/aD05NjE7dz0xNDQwO2FwcGlkPXl0YWNoeW9u/https://media.zenfs.com/en/bizjournals.com/3dac5c71dcec6f23c909bd14151b3b83",
                    "width": 140,
                    "height": 140,
                    "tag": "140x140"
                }
            ]
        },
        "relatedTickers": [
            "AMZN"
        ]
    },
    "b4c9b0e1-b804-4cf2-bb79-c607608455c2": {
        "uuid": "b4c9b0e1-b804-4cf2-bb79-c607608455c2",
        "title": "'A one-time thing': Analyst details Netflix's risky $200 million bet on 'The Gray Man'",
        "publisher": "Yahoo Finance",
        "link": "https://finance.yahoo.com/news/a-one-time-thing-analyst-details-netflix-risky-200-million-on-the-gray-man-203529309.html",
        "providerPublishTime": 1658522129,
        "type": "STORY",
        "thumbnail": {
            "resolutions": [
                {
                    "url": "https://s.yimg.com/uu/api/res/1.2/rZwnq52IOfAVp37Rempg7w--~B/aD0xMzY1O3c9MjA0ODthcHBpZD15dGFjaHlvbg--/https://s.yimg.com/os/creatr-uploaded-images/2022-07/0c941e30-090a-11ed-abef-48f6e9dd9a21",
                    "width": 2048,
                    "height": 1365,
                    "tag": "original"
                },
                {
                    "url": "https://s.yimg.com/uu/api/res/1.2/lihokPm1estVlQzq6taN5g--~B/Zmk9ZmlsbDtoPTE0MDtweW9mZj0wO3c9MTQwO2FwcGlkPXl0YWNoeW9u/https://s.yimg.com/os/creatr-uploaded-images/2022-07/0c941e30-090a-11ed-abef-48f6e9dd9a21",
                    "width": 140,
                    "height": 140,
                    "tag": "140x140"
                }
            ]
        },
        "relatedTickers": [
            "DIS",
            "CMCSA",
            "NFLX",
            "AMZN"
        ]
    }
}