{
    "d17cde2b-37ef-39df-b28c-f5db93e85b5f": {
        "uuid": "d17cde2b-37ef-39df-b28c-f5db93e85b5f",
        "title": "Energy Transfer LP (ET) Stock Sinks As Market Gains: What You Should Know",
        "publisher": "Zacks",
        "link": "https://finance.yahoo.com/news/energy-transfer-lp-et-stock-214509295.html",
        "providerPublishTime": 1657057509,
        "type": "STORY",
        "thumbnail": {
            "resolutions": [
                {
                    "url": "https://s.yimg.com/uu/api/res/1.2/oMKb0aDck8IpQx0xUmmnpQ--~B/aD02MTg7dz05MDA7YXBwaWQ9eXRhY2h5b24-/https://s.yimg.com/uu/api/res/1.2/bHsRpCKrGzzbaGHEolBtWw--~B/aD02MTg7dz05MDA7YXBwaWQ9eXRhY2h5b24-/https://media.zenfs.com/en/zacks.com/023168c7ea091c342492be3899b280af",
                    "width": 900,
                    "height": 618,
                    "tag": "original"
                },
                {
                    "url": "https://s.yimg.com/uu/api/res/1.2/az2jqXhqyZRic77Cn4mQiQ--~B/Zmk9ZmlsbDtoPTE0MDtweW9mZj0wO3c9MTQwO2FwcGlkPXl0YWNoeW9u/https://s.yimg.com/uu/api/res/1.2/bHsRpCKrGzzbaGHEolBtWw--~B/aD02MTg7dz05MDA7YXBwaWQ9eXRhY2h5b24-/https://media.zenfs.com/en/zacks.com/023168c7ea091c342492be3899b280af",
                    "width": 140,
                    "height": 140,
                    "tag": "140x140"
                }
            ]
        },
        "relatedTickers": [
            "ET-PD",
            "^GSPC"
        ]
    },
    "1d9ae2c8-0a4a-3efe-88f0-8d0e904c9cda": {
        "uuid": "1d9ae2c8-0a4a-3efe-88f0-8d0e904c9cda",
        "title": "Energy Transfer LP (ET) Is a Trending Stock: Facts to Know Before Betting on It",
        "publisher": "Zacks",
        "link": "https://finance.yahoo.com/news/energy-transfer-lp-et-trending-130001911.html",
        "providerPublishTime": 1656939601,
        "type": "STORY",
        "thumbnail": {
            "resolutions": [
                {
                    "url": "https://s.yimg.com/uu/api/res/1.2/ffKO.4EbCj1BJM65zWy0mg--~B/aD02MDE7dz05MDA7YXBwaWQ9eXRhY2h5b24-/https://s.yimg.com/uu/api/res/1.2/QOfludHza1dTKV8R6Coeiw--~B/aD02MDE7dz05MDA7YXBwaWQ9eXRhY2h5b24-/https://media.zenfs.com/en/zacks.com/48ad4265c55e3ba7a1fb9148d6e717d9",
                    "width": 900,
                    "height": 601,
                    "tag": "original"
                },
                {
                    "url": "https://s.yimg.com/uu/api/res/1.2/95p02wXX_mPZm4qTHztw1w--~B/Zmk9ZmlsbDtoPTE0MDtweW9mZj0wO3c9MTQwO2FwcGlkPXl0YWNoeW9u/https://s.yimg.com/uu/api/res/1.2/QOfludHza1dTKV8R6Coeiw--~B/aD02MDE7dz05MDA7YXBwaWQ9eXRhY2h5b24-/https://media.zenfs.com/en/zacks.com/48ad4265c55e3ba7a1fb9148d6e717d9",
                    "width": 140,
                    "height": 140,
                    "tag": "140x140"
                }
            ]
        },
        "relatedTickers": [
            "ET-PD"
        ]
    },
    "09dd68a9-7ca7-3a4a-9fc1-4d2e602900a9": {
        "uuid": "09dd68a9-7ca7-3a4a-9fc1-4d2e602900a9",
        "title": "3 Passive Income Opportunities the Bear Market Has Churned Up",
        "publisher": "Motley Fool",
        "link": "https://finance.yahoo.com/m/09dd68a9-7ca7-3a4a-9fc1-4d2e602900a9/3-passive-income.html",
        "providerPublishTime": 1656768600,
        "type": "STORY",
        "relatedTickers": [
            "PSX",
            "ET-PD"
        ]
    },
    "bbacd2b8-df8b-3a33-a986-3e8c87f57b83": {
        "uuid": "bbacd2b8-df8b-3a33-a986-3e8c87f57b83",
        "title": "Energy Transfer LP (ET) Gains As Market Dips: What You Should Know",
        "publisher": "Zacks",
        "link": "https://finance.yahoo.com/news/energy-transfer-lp-et-gains-214509564.html",
        "providerPublishTime": 1656366309,
        "type": "STORY",
        "thumbnail": {
            "resolutions": [
                {
                    "url": "https://s.yimg.com/uu/api/res/1.2/SAL_BV4Lqcz677Hwp3FpIw--~B/aD02MDM7dz0xMDAwO2FwcGlkPXl0YWNoeW9u/https://s.yimg.com/uu/api/res/1.2/Fs_R4sd8jCoOMib958Znmg--~B/aD02MDM7dz0xMDAwO2FwcGlkPXl0YWNoeW9u/https://media.zenfs.com/en/zacks.com/432476d296d64c50172213c0415587c9",
                    "width": 1000,
                    "height": 603,
                    "tag": "original"
                },
                {
                    "url": "https://s.yimg.com/uu/api/res/1.2/UFSM7lesnJ4LZBk9Z57AzA--~B/Zmk9ZmlsbDtoPTE0MDtweW9mZj0wO3c9MTQwO2FwcGlkPXl0YWNoeW9u/https://s.yimg.com/uu/api/res/1.2/Fs_R4sd8jCoOMib958Znmg--~B/aD02MDM7dz0xMDAwO2FwcGlkPXl0YWNoeW9u/https://media.zenfs.com/en/zacks.com/432476d296d64c50172213c0415587c9",
                    "width": 140,
                    "height": 140,
                    "tag": "140x140"
                }
            ]
        },
        "relatedTickers": [
            "ET-PD",
            "^GSPC"
        ]
    },
    "438fdef3-25bb-35cd-a2d4-d7af60ada061": {
        "uuid": "438fdef3-25bb-35cd-a2d4-d7af60ada061",
        "title": "PBF Logistics LP (PBFX) Stock Jumps 10.5%: Will It Continue to Soar?",
        "publisher": "Zacks",
        "link": "https://finance.yahoo.com/news/pbf-logistics-lp-pbfx-stock-124712917.html",
        "providerPublishTime": 1656334032,
        "type": "STORY",
        "thumbnail": {
            "resolutions": [
                {
                    "url": "https://s.yimg.com/uu/api/res/1.2/hbGi6DNvr5JP4FnpdaDqOw--~B/aD02MDA7dz05MDA7YXBwaWQ9eXRhY2h5b24-/https://s.yimg.com/uu/api/res/1.2/rKKQU6icFw_cY7r5zs2jVg--~B/aD02MDA7dz05MDA7YXBwaWQ9eXRhY2h5b24-/https://media.zenfs.com/en/zacks.com/6c6532143bb000630dd2c034345ca622",
                    "width": 900,
                    "height": 600,
                    "tag": "original"
                },
                {
                    "url": "https://s.yimg.com/uu/api/res/1.2/NSC_4BKFAcuSKO3qqS2hzQ--~B/Zmk9ZmlsbDtoPTE0MDtweW9mZj0wO3c9MTQwO2FwcGlkPXl0YWNoeW9u/https://s.yimg.com/uu/api/res/1.2/rKKQU6icFw_cY7r5zs2jVg--~B/aD02MDA7dz05MDA7YXBwaWQ9eXRhY2h5b24-/https://media.zenfs.com/en/zacks.com/6c6532143bb000630dd2c034345ca622",
                    "width": 140,
                    "height": 140,
                    "tag": "140x140"
                }
            ]
        },
        "relatedTickers": [
            "PBFX",
            "ET-PD"
        ]
    },
    "c4e8639a-ed62-3e57-9163-3edced909d01": {
        "uuid": "c4e8639a-ed62-3e57-9163-3edced909d01",
        "title": "6 High-Yield Stocks With Good Upside Potential",
        "publisher": "InvestorPlace",
        "link": "https://finance.yahoo.com/news/6-high-yield-stocks-good-102153802.html",
        "providerPublishTime": 1656325313,
        "type": "STORY",
        "thumbnail": {
            "resolutions": [
                {
                    "url": "https://s.yimg.com/uu/api/res/1.2/Kn2lJSpr6xTJavsCydzYqA--~B/aD00MDA7dz03Mjg7YXBwaWQ9eXRhY2h5b24-/https://s.yimg.com/uu/api/res/1.2/2ulRQQ_vXAlvdBG98on8lA--~B/aD00MDA7dz03Mjg7YXBwaWQ9eXRhY2h5b24-/https://media.zenfs.com/en/investorplace_417/4bf27f13cc4d00f608f26c61f89fa923",
                    "width": 728,
                    "height": 400,
                    "tag": "original"
                },
                {
                    "url": "https://s.yimg.com/uu/api/res/1.2/kZRW9xMWphUw2v.g0MsdTw--~B/Zmk9ZmlsbDtoPTE0MDtweW9mZj0wO3c9MTQwO2FwcGlkPXl0YWNoeW9u/https://s.yimg.com/uu/api/res/1.2/2ulRQQ_vXAlvdBG98on8lA--~B/aD00MDA7dz03Mjg7YXBwaWQ9eXRhY2h5b24-/https://media.zenfs.com/en/investorplace_417/4bf27f13cc4d00f608f26c61f89fa923",
                    "width": 140,
                    "height": 140,
                    "tag": "140x140"
                }
            ]
        },
        "relatedTickers": [
            "STOR",
            "KT",
            "DVN",
            "ET-PD",
            "LYB",
            "SRC"
        ]
    },
    "34ad2a72-8cf1-386b-90c7-4a071e5dc6c1": {
        "uuid": "34ad2a72-8cf1-386b-90c7-4a071e5dc6c1",
        "title": "3 High-Yield Dividend Stocks That Could Soar",
        "publisher": "Motley Fool",
        "link": "https://finance.yahoo.com/m/34ad2a72-8cf1-386b-90c7-4a071e5dc6c1/3-high-yield-dividend-stocks.html",
        "providerPublishTime": 1656071400,
        "type": "STORY",
        "thumbnail": {
            "resolutions": [
                {
                    "url": "https://s.yimg.com/uu/api/res/1.2/y.dynWW.j.NfDuxwwYi57Q--~B/aD05MzM7dz0xNDAwO2FwcGlkPXl0YWNoeW9u/https://s.yimg.com/uu/api/res/1.2/KO0xpHalYOQQkgSqyvetBQ--~B/aD05MzM7dz0xNDAwO2FwcGlkPXl0YWNoeW9u/https://media.zenfs.com/en/motleyfool.com/23eb1cb5ad54b9a1acf65c72b1c00ed5",
                    "width": 1400,
                    "height": 933,
                    "tag": "original"
                },
                {
                    "url": "https://s.yimg.com/uu/api/res/1.2/9zzqpv._2y5YBZlVmfFh1g--~B/Zmk9ZmlsbDtoPTE0MDtweW9mZj0wO3c9MTQwO2FwcGlkPXl0YWNoeW9u/https://s.yimg.com/uu/api/res/1.2/KO0xpHalYOQQkgSqyvetBQ--~B/aD05MzM7dz0xNDAwO2FwcGlkPXl0YWNoeW9u/https://media.zenfs.com/en/motleyfool.com/23eb1cb5ad54b9a1acf65c72b1c00ed5",
                    "width": 140,
                    "height": 140,
                    "tag": "140x140"
                }
            ]
        },
        "relatedTickers": [
            "MAIN",
            "ET-PD",
            "WEC"
        ]
    },
    "7f878751-886f-32c2-a07f-1e0428243247": {
        "uuid": "7f878751-886f-32c2-a07f-1e0428243247",
        "title": "David Abrams\u2019 2022 Portfolio: Top 10 Stock Picks",
        "publisher": "Insider Monkey",
        "link": "https://finance.yahoo.com/news/david-abrams-2022-portfolio-top-130048953.html",
        "providerPublishTime": 1655989248,
        "type": "STORY",
        "thumbnail": {
            "resolutions": [
                {
                    "url": "https://s.yimg.com/uu/api/res/1.2/jRdmrBQShrXbMkKRbaJ1bA--~B/aD02MDA7dz00NTA7YXBwaWQ9eXRhY2h5b24-/https://s.yimg.com/uu/api/res/1.2/hg_sy_Vgsx0w7ilYQ0RO6A--~B/aD02MDA7dz00NTA7YXBwaWQ9eXRhY2h5b24-/https://media.zenfs.com/en/insidermonkey.com/dd66b0dc13c3c0eeb3b19fd808662454",
                    "width": 450,
                    "height": 600,
                    "tag": "original"
                },
                {
                    "url": "https://s.yimg.com/uu/api/res/1.2/fK5IEU5SB5ZRpRD52myj0Q--~B/Zmk9ZmlsbDtoPTE0MDtweW9mZj0wO3c9MTQwO2FwcGlkPXl0YWNoeW9u/https://s.yimg.com/uu/api/res/1.2/hg_sy_Vgsx0w7ilYQ0RO6A--~B/aD02MDA7dz00NTA7YXBwaWQ9eXRhY2h5b24-/https://media.zenfs.com/en/insidermonkey.com/dd66b0dc13c3c0eeb3b19fd808662454",
                    "width": 140,
                    "height": 140,
                    "tag": "140x140"
                }
            ]
        },
        "relatedTickers": [
            "ET-PD",
            "UHAL",
            "META",
            "WTW",
            "CPNG",
            "CHNG",
            "GOOGL",
            "TDG"
        ]
    }
}